WizzHash.py
WizzHash-2.0.dist-info/LICENSE.txt
WizzHash-2.0.dist-info/METADATA
WizzHash-2.0.dist-info/WHEEL
WizzHash-2.0.dist-info/top_level.txt
WizzHash-2.0.dist-info/RECORD
