Metadata-Version: 2.1
Name: WizzHash
Version: 2.0
Summary: wifi listing
Home-page: https://github.com/WIZARD00007/wizzHashing
Author: Akshay
Author-email: akshaysavanoor@gmail.com
License: UNKNOWN
Platform: UNKNOWN
Classifier: Programming Language :: Python :: 3
Classifier: Programming Language :: Python :: 3.7
Classifier: Programming Language :: Python :: 3.10
Classifier: License :: OSI Approved :: GNU General Public License v2 or later (GPLv2+)
Classifier: Operating System :: OS Independent
License-File: LICENSE.txt
Requires-Dist: blessings (~=1.7)
